LICENSE
SAMPLES.md
gs_aws_to_gcp_workload_identity/.env
gs_aws_to_gcp_workload_identity/__init__.py
gs_aws_to_gcp_workload_identity/gcp_token.py
gs_aws_to_gcp_workload_identity/gcp_util.py
gs_aws_to_gcp_workload_identity/main.py
gs_aws_to_gcp_workload_identity-0.1.4.dist-info/LICENSE
gs_aws_to_gcp_workload_identity-0.1.4.dist-info/WHEEL
gs_aws_to_gcp_workload_identity-0.1.4.dist-info/METADATA
gs_aws_to_gcp_workload_identity-0.1.4.dist-info/RECORD
