Metadata-Version: 2.1
Name: gs-aws-to-gcp-workload-identity
Version: 0.1.4
Summary: Helper for obtaining GCP Tokens via AWS-to-GCP Workload Identity Federation
Home-page: https://github.com/ghostsecurity/gs-aws-to-gcp-workload-identity
License: MIT
Keywords: aws,gcp,workload,identity,federation
Author: Ghost Security
Author-email: info@ghost.security
Requires-Python: >=3.9,<4.0
Classifier: License :: OSI Approved :: MIT License
Classifier: Programming Language :: Python :: 3
Classifier: Programming Language :: Python :: 3.10
Classifier: Programming Language :: Python :: 3.9
Requires-Dist: boto3 (>=1.24.40,<2.0.0)
Requires-Dist: botocore (>=1.27.40,<2.0.0)
Requires-Dist: google-auth (>=2.9.1,<3.0.0)
Requires-Dist: jwt (>=1.3.1,<2.0.0)
Requires-Dist: requests (>=2.28.1,<3.0.0)
Project-URL: Repository, https://github.com/ghostsecurity/gs-aws-to-gcp-workload-identity
